[
    {
        "abbr": "1-musa",
        "category_id": 1,
        "id": 1,
        "name": "1 Musa",
        "number_of_chapters": 50,
        "sort_order": 10
    },
    {
        "abbr": "2-musa",
        "category_id": 1,
        "id": 2,
        "name": "2 Musa",
        "number_of_chapters": 40,
        "sort_order": 20
    },
    {
        "abbr": "3-musa",
        "category_id": 1,
        "id": 3,
        "name": "3 Musa",
        "number_of_chapters": 27,
        "sort_order": 30
    },
    {
        "abbr": "4-musa",
        "category_id": 1,
        "id": 4,
        "name": "4 Musa",
        "number_of_chapters": 36,
        "sort_order": 40
    },
    {
        "abbr": "5-musa",
        "category_id": 1,
        "id": 5,
        "name": "5 Musa",
        "number_of_chapters": 34,
        "sort_order": 50
    },
    {
        "abbr": "josua",
        "category_id": 1,
        "id": 6,
        "name": "Josua",
        "number_of_chapters": 24,
        "sort_order": 60
    },
    {
        "abbr": "panguhum",
        "category_id": 1,
        "id": 7,
        "name": "Panguhum",
        "number_of_chapters": 21,
        "sort_order": 70
    },
    {
        "abbr": "rut",
        "category_id": 1,
        "id": 8,
        "name": "Rut",
        "number_of_chapters": 4,
        "sort_order": 80
    },
    {
        "abbr": "1-samuel",
        "category_id": 1,
        "id": 9,
        "name": "1 Samuel",
        "number_of_chapters": 31,
        "sort_order": 90
    },
    {
        "abbr": "2-samuel",
        "category_id": 1,
        "id": 10,
        "name": "2 Samuel",
        "number_of_chapters": 24,
        "sort_order": 100
    },
    {
        "abbr": "1-raja-raja",
        "category_id": 1,
        "id": 11,
        "name": "1 Raja-raja",
        "number_of_chapters": 22,
        "sort_order": 110
    },
    {
        "abbr": "2-raja-raja",
        "category_id": 1,
        "id": 12,
        "name": "2 Raja-raja",
        "number_of_chapters": 25,
        "sort_order": 120
    },
    {
        "abbr": "1-kronika",
        "category_id": 1,
        "id": 13,
        "name": "1 Kronika",
        "number_of_chapters": 29,
        "sort_order": 130
    },
    {
        "abbr": "2-kronika",
        "category_id": 1,
        "id": 14,
        "name": "2 Kronika",
        "number_of_chapters": 36,
        "sort_order": 140
    },
    {
        "abbr": "esra",
        "category_id": 1,
        "id": 15,
        "name": "Esra",
        "number_of_chapters": 10,
        "sort_order": 150
    },
    {
        "abbr": "nehemia",
        "category_id": 1,
        "id": 16,
        "name": "Nehemia",
        "number_of_chapters": 13,
        "sort_order": 160
    },
    {
        "abbr": "ester",
        "category_id": 1,
        "id": 17,
        "name": "Ester",
        "number_of_chapters": 10,
        "sort_order": 170
    },
    {
        "abbr": "job",
        "category_id": 1,
        "id": 18,
        "name": "Job",
        "number_of_chapters": 42,
        "sort_order": 180
    },
    {
        "abbr": "psalmen",
        "category_id": 1,
        "id": 19,
        "name": "Psalmen",
        "number_of_chapters": 150,
        "sort_order": 190
    },
    {
        "abbr": "poda",
        "category_id": 1,
        "id": 20,
        "name": "Poda",
        "number_of_chapters": 31,
        "sort_order": 200
    },
    {
        "abbr": "parjamita",
        "category_id": 1,
        "id": 21,
        "name": "Parjamita",
        "number_of_chapters": 12,
        "sort_order": 210
    },
    {
        "abbr": "angka-ende",
        "category_id": 1,
        "id": 22,
        "name": "Angka Ende",
        "number_of_chapters": 8,
        "sort_order": 220
    },
    {
        "abbr": "jesaya",
        "category_id": 1,
        "id": 23,
        "name": "Jesaya",
        "number_of_chapters": 66,
        "sort_order": 230
    },
    {
        "abbr": "jeremia",
        "category_id": 1,
        "id": 24,
        "name": "Jeremia",
        "number_of_chapters": 52,
        "sort_order": 240
    },
    {
        "abbr": "andung-andung",
        "category_id": 1,
        "id": 25,
        "name": "Andung-andung",
        "number_of_chapters": 5,
        "sort_order": 250
    },
    {
        "abbr": "hesekiel",
        "category_id": 1,
        "id": 26,
        "name": "Hesekiel",
        "number_of_chapters": 48,
        "sort_order": 260
    },
    {
        "abbr": "daniel",
        "category_id": 1,
        "id": 27,
        "name": "Daniel",
        "number_of_chapters": 12,
        "sort_order": 270
    },
    {
        "abbr": "hosea",
        "category_id": 1,
        "id": 28,
        "name": "Hosea",
        "number_of_chapters": 14,
        "sort_order": 280
    },
    {
        "abbr": "joel",
        "category_id": 1,
        "id": 29,
        "name": "Joel",
        "number_of_chapters": 3,
        "sort_order": 290
    },
    {
        "abbr": "amos",
        "category_id": 1,
        "id": 30,
        "name": "Amos",
        "number_of_chapters": 9,
        "sort_order": 300
    },
    {
        "abbr": "obaja",
        "category_id": 1,
        "id": 31,
        "name": "Obaja",
        "number_of_chapters": 1,
        "sort_order": 310
    },
    {
        "abbr": "jona",
        "category_id": 1,
        "id": 32,
        "name": "Jona",
        "number_of_chapters": 4,
        "sort_order": 320
    },
    {
        "abbr": "mika",
        "category_id": 1,
        "id": 33,
        "name": "Mika",
        "number_of_chapters": 7,
        "sort_order": 330
    },
    {
        "abbr": "nahum",
        "category_id": 1,
        "id": 34,
        "name": "Nahum",
        "number_of_chapters": 3,
        "sort_order": 340
    },
    {
        "abbr": "habakuk",
        "category_id": 1,
        "id": 35,
        "name": "Habakuk",
        "number_of_chapters": 3,
        "sort_order": 350
    },
    {
        "abbr": "sepania",
        "category_id": 1,
        "id": 36,
        "name": "Sepania",
        "number_of_chapters": 3,
        "sort_order": 360
    },
    {
        "abbr": "haggai",
        "category_id": 1,
        "id": 37,
        "name": "Haggai",
        "number_of_chapters": 2,
        "sort_order": 370
    },
    {
        "abbr": "sakaria",
        "category_id": 1,
        "id": 38,
        "name": "Sakaria",
        "number_of_chapters": 14,
        "sort_order": 380
    },
    {
        "abbr": "maleaki",
        "category_id": 1,
        "id": 39,
        "name": "Maleaki",
        "number_of_chapters": 4,
        "sort_order": 390
    },
    {
        "abbr": "mateus",
        "category_id": 2,
        "id": 40,
        "name": "Mateus",
        "number_of_chapters": 28,
        "sort_order": 400
    },
    {
        "abbr": "markus",
        "category_id": 2,
        "id": 41,
        "name": "Markus",
        "number_of_chapters": 16,
        "sort_order": 410
    },
    {
        "abbr": "lukas",
        "category_id": 2,
        "id": 42,
        "name": "Lukas",
        "number_of_chapters": 24,
        "sort_order": 420
    },
    {
        "abbr": "johannes",
        "category_id": 2,
        "id": 43,
        "name": "Johannes",
        "number_of_chapters": 21,
        "sort_order": 430
    },
    {
        "abbr": "ulaon-ni-apostel",
        "category_id": 2,
        "id": 44,
        "name": "Ulaon ni Apostel",
        "number_of_chapters": 28,
        "sort_order": 440
    },
    {
        "abbr": "rom",
        "category_id": 2,
        "id": 45,
        "name": "Rom",
        "number_of_chapters": 16,
        "sort_order": 450
    },
    {
        "abbr": "1-korint",
        "category_id": 2,
        "id": 46,
        "name": "1 Korint",
        "number_of_chapters": 16,
        "sort_order": 460
    },
    {
        "abbr": "2-korint",
        "category_id": 2,
        "id": 47,
        "name": "2 Korint",
        "number_of_chapters": 13,
        "sort_order": 470
    },
    {
        "abbr": "galatia",
        "category_id": 2,
        "id": 48,
        "name": "Galatia",
        "number_of_chapters": 6,
        "sort_order": 480
    },
    {
        "abbr": "epesus",
        "category_id": 2,
        "id": 49,
        "name": "Epesus",
        "number_of_chapters": 6,
        "sort_order": 490
    },
    {
        "abbr": "pilippi",
        "category_id": 2,
        "id": 50,
        "name": "Pilippi",
        "number_of_chapters": 4,
        "sort_order": 500
    },
    {
        "abbr": "kolosse",
        "category_id": 2,
        "id": 51,
        "name": "Kolosse",
        "number_of_chapters": 4,
        "sort_order": 510
    },
    {
        "abbr": "1-tessalonik",
        "category_id": 2,
        "id": 52,
        "name": "1 Tessalonik",
        "number_of_chapters": 5,
        "sort_order": 520
    },
    {
        "abbr": "2-tessalonik",
        "category_id": 2,
        "id": 53,
        "name": "2 Tessalonik",
        "number_of_chapters": 3,
        "sort_order": 530
    },
    {
        "abbr": "1-timoteus",
        "category_id": 2,
        "id": 54,
        "name": "1 Timoteus",
        "number_of_chapters": 6,
        "sort_order": 540
    },
    {
        "abbr": "2-timoteus",
        "category_id": 2,
        "id": 55,
        "name": "2 Timoteus",
        "number_of_chapters": 4,
        "sort_order": 550
    },
    {
        "abbr": "titus",
        "category_id": 2,
        "id": 56,
        "name": "Titus",
        "number_of_chapters": 3,
        "sort_order": 560
    },
    {
        "abbr": "pilemon",
        "category_id": 2,
        "id": 57,
        "name": "Pilemon",
        "number_of_chapters": 1,
        "sort_order": 570
    },
    {
        "abbr": "heber",
        "category_id": 2,
        "id": 58,
        "name": "Heber",
        "number_of_chapters": 13,
        "sort_order": 580
    },
    {
        "abbr": "jakobus",
        "category_id": 2,
        "id": 59,
        "name": "Jakobus",
        "number_of_chapters": 5,
        "sort_order": 590
    },
    {
        "abbr": "1-petrus",
        "category_id": 2,
        "id": 60,
        "name": "1 Petrus",
        "number_of_chapters": 5,
        "sort_order": 600
    },
    {
        "abbr": "2-petrus",
        "category_id": 2,
        "id": 61,
        "name": "2 Petrus",
        "number_of_chapters": 3,
        "sort_order": 610
    },
    {
        "abbr": "1-jonannes",
        "category_id": 2,
        "id": 62,
        "name": "1 Johannes",
        "number_of_chapters": 5,
        "sort_order": 620
    },
    {
        "abbr": "2-johannes",
        "category_id": 2,
        "id": 63,
        "name": "2 Johannes",
        "number_of_chapters": 1,
        "sort_order": 630
    },
    {
        "abbr": "3-johannes",
        "category_id": 2,
        "id": 64,
        "name": "3 Johannes",
        "number_of_chapters": 1,
        "sort_order": 640
    },
    {
        "abbr": "judas",
        "category_id": 2,
        "id": 65,
        "name": "Judas",
        "number_of_chapters": 1,
        "sort_order": 650
    },
    {
        "abbr": "pangungkapon",
        "category_id": 2,
        "id": 66,
        "name": "Pangungkapon",
        "number_of_chapters": 22,
        "sort_order": 660
    }
]